persian_dict/__init__.py
persian_dict/core.py
persian_dict/data_models.py
persian_dict/exceptions.py
persian_dict/randomizer.py
persian_dict/search.py
persian_dict/utils.py
persian_dict-1.0.0.dist-info/METADATA
persian_dict-1.0.0.dist-info/WHEEL
persian_dict-1.0.0.dist-info/entry_points.txt
persian_dict-1.0.0.dist-info/top_level.txt
persian_dict-1.0.0.dist-info/RECORD
